{
  "title": "2013 Single Audit Report (PDF)",
  "url": "https://www.townofriverheadny.gov/DocumentCenter/View/312/2013-Single-Audit-Report-PDF",
  "year": 2013,
  "category": "audit",
  "slug": "2013-2013-single-audit-report-pdf",
  "sha256": "40ddee88c2b677886ef5610c828a64865e47a7907548d6991dd8bfa931aa487f",
  "page_count": 26,
  "money_value_count": 0,
  "pages": [
    {
      "page": 1,
      "text": "",
      "money_values": [],
      "line_count": 0,
      "confidence": "low"
    },
    {
      "page": 2,
      "text": "",
      "money_values": [],
      "line_count": 0,
      "confidence": "low"
    },
    {
      "page": 3,
      "text": "",
      "money_values": [],
      "line_count": 0,
      "confidence": "low"
    },
    {
      "page": 4,
      "text": "",
      "money_values": [],
      "line_count": 0,
      "confidence": "low"
    },
    {
      "page": 5,
      "text": "",
      "money_values": [],
      "line_count": 0,
      "confidence": "low"
    },
    {
      "page": 6,
      "text": "",
      "money_values": [],
      "line_count": 0,
      "confidence": "low"
    },
    {
      "page": 7,
      "text": "",
      "money_values": [],
      "line_count": 0,
      "confidence": "low"
    },
    {
      "page": 8,
      "text": "",
      "money_values": [],
      "line_count": 0,
      "confidence": "low"
    },
    {
      "page": 9,
      "text": "",
      "money_values": [],
      "line_count": 0,
      "confidence": "low"
    },
    {
      "page": 10,
      "text": "",
      "money_values": [],
      "line_count": 0,
      "confidence": "low"
    },
    {
      "page": 11,
      "text": "",
      "money_values": [],
      "line_count": 0,
      "confidence": "low"
    },
    {
      "page": 12,
      "text": "",
      "money_values": [],
      "line_count": 0,
      "confidence": "low"
    },
    {
      "page": 13,
      "text": "",
      "money_values": [],
      "line_count": 0,
      "confidence": "low"
    },
    {
      "page": 14,
      "text": "",
      "money_values": [],
      "line_count": 0,
      "confidence": "low"
    },
    {
      "page": 15,
      "text": "",
      "money_values": [],
      "line_count": 0,
      "confidence": "low"
    },
    {
      "page": 16,
      "text": "",
      "money_values": [],
      "line_count": 0,
      "confidence": "low"
    },
    {
      "page": 17,
      "text": "",
      "money_values": [],
      "line_count": 0,
      "confidence": "low"
    },
    {
      "page": 18,
      "text": "",
      "money_values": [],
      "line_count": 0,
      "confidence": "low"
    },
    {
      "page": 19,
      "text": "",
      "money_values": [],
      "line_count": 0,
      "confidence": "low"
    },
    {
      "page": 20,
      "text": "",
      "money_values": [],
      "line_count": 0,
      "confidence": "low"
    },
    {
      "page": 21,
      "text": "",
      "money_values": [],
      "line_count": 0,
      "confidence": "low"
    },
    {
      "page": 22,
      "text": "",
      "money_values": [],
      "line_count": 0,
      "confidence": "low"
    },
    {
      "page": 23,
      "text": "",
      "money_values": [],
      "line_count": 0,
      "confidence": "low"
    },
    {
      "page": 24,
      "text": "",
      "money_values": [],
      "line_count": 0,
      "confidence": "low"
    },
    {
      "page": 25,
      "text": "",
      "money_values": [],
      "line_count": 0,
      "confidence": "low"
    },
    {
      "page": 26,
      "text": "",
      "money_values": [],
      "line_count": 0,
      "confidence": "low"
    }
  ],
  "parsed_at": "2026-07-21T03:53:57.483465+00:00"
}